{
  "version": 1,
  "baseResolutionNote": "Coordinates follow MAA-style scaling from baseResolution to the active device resolution.",
  "profiles": [
    {
      "id": "runStatusFull",
      "label": "基本情報スキャン",
      "triggerPath": "/trigger/scan/run/status",
      "candidateKind": "runStatus",
      "baseResolution": {
        "width": 1280,
        "height": 720
      },
      "knownScreenIds": [
        "run-home",
        "run-status"
      ],
      "openSteps": [
        {
          "type": "tap",
          "point": {
            "x": 54,
            "y": 677
          },
          "label": "左下の分隊情報を開く",
          "area": {
            "x": 12,
            "y": 634,
            "width": 84,
            "height": 86
          }
        },
        {
          "type": "wait",
          "durationMs": 220,
          "label": "表示待ち"
        }
      ],
      "scanRegion": {
        "x": 700,
        "y": 24,
        "width": 540,
        "height": 92
      },
      "scrollAxis": "none",
      "scrollDirection": "none",
      "restoreSteps": [
        {
          "type": "back",
          "label": "分隊情報を閉じる"
        }
      ],
      "maxScrolls": 0,
      "endFingerprintStableCount": 1,
      "captureDelayMs": 180,
      "inferredScreenId": "run-squad-info-panel",
      "navigationNote": "分隊は左下をクリックすると等級と同時に表示される。構想は思案の右側に表示される数値を別ROIで読む。"
    },
    {
      "id": "operatorsFull",
      "label": "オペレーターフルスキャン",
      "triggerPath": "/trigger/scan/operators/full",
      "candidateKind": "operator",
      "baseResolution": {
        "width": 1280,
        "height": 720
      },
      "knownScreenIds": [
        "run-home",
        "operator-list",
        "squad-list"
      ],
      "openSteps": [
        {
          "type": "tap",
          "point": {
            "x": 948,
            "y": 678
          },
          "label": "隊員を開く",
          "area": {
            "x": 904,
            "y": 645,
            "width": 88,
            "height": 66
          }
        },
        {
          "type": "wait",
          "durationMs": 220,
          "label": "表示待ち"
        }
      ],
      "scanRegion": {
        "x": 90,
        "y": 84,
        "width": 1100,
        "height": 540
      },
      "scrollAxis": "vertical",
      "scrollDirection": "down",
      "scroll": {
        "start": {
          "x": 1080,
          "y": 610
        },
        "end": {
          "x": 1080,
          "y": 180
        },
        "durationMs": 450
      },
      "restoreSteps": [
        {
          "type": "back",
          "label": "元画面へ戻る"
        }
      ],
      "maxScrolls": 18,
      "endFingerprintStableCount": 2,
      "captureDelayMs": 160,
      "navigationNote": "隊員表示をクリックして招集済みオペレーター一覧を開く。"
    },
    {
      "id": "relicsFull",
      "label": "秘宝フルスキャン",
      "triggerPath": "/trigger/scan/relics/full",
      "candidateKind": "relic",
      "baseResolution": {
        "width": 1280,
        "height": 720
      },
      "knownScreenIds": [
        "run-home",
        "relic-list"
      ],
      "openSteps": [
        {
          "type": "tap",
          "point": {
            "x": 176,
            "y": 678
          },
          "label": "右側の秘宝を開く",
          "area": {
            "x": 134,
            "y": 648,
            "width": 84,
            "height": 60
          }
        },
        {
          "type": "wait",
          "durationMs": 220,
          "label": "表示待ち"
        }
      ],
      "scanRegion": {
        "x": 90,
        "y": 84,
        "width": 1100,
        "height": 540
      },
      "scrollAxis": "vertical",
      "scrollDirection": "down",
      "scroll": {
        "start": {
          "x": 1080,
          "y": 610
        },
        "end": {
          "x": 1080,
          "y": 180
        },
        "durationMs": 450
      },
      "restoreSteps": [
        {
          "type": "back",
          "label": "元画面へ戻る"
        }
      ],
      "maxScrolls": 20,
      "endFingerprintStableCount": 2,
      "captureDelayMs": 160,
      "navigationNote": "右側の秘宝表示をクリックして秘宝一覧を開く。"
    },
    {
      "id": "is4RevelationFull",
      "label": "啓示フルスキャン",
      "triggerPath": "/trigger/scan/sami/revelation",
      "campaignId": "is4_sami",
      "candidateKind": "revelation",
      "baseResolution": {
        "width": 1280,
        "height": 720
      },
      "knownScreenIds": [
        "run-home",
        "sami-revelation-list"
      ],
      "openSteps": [],
      "scanRegion": {
        "x": 90,
        "y": 84,
        "width": 1100,
        "height": 540
      },
      "scrollAxis": "vertical",
      "scrollDirection": "down",
      "scroll": {
        "start": {
          "x": 1080,
          "y": 610
        },
        "end": {
          "x": 1080,
          "y": 180
        },
        "durationMs": 450
      },
      "restoreSteps": [
        {
          "type": "back",
          "label": "元画面へ戻る"
        }
      ],
      "maxScrolls": 16,
      "endFingerprintStableCount": 2,
      "captureDelayMs": 160
    },
    {
      "id": "is5ThoughtFull",
      "label": "思案フルスキャン",
      "triggerPath": "/trigger/scan/sarkaz/thought",
      "campaignId": "is5_sarkaz",
      "candidateKind": "thought",
      "baseResolution": {
        "width": 1280,
        "height": 720
      },
      "knownScreenIds": [
        "run-home",
        "sarkaz-thought-list"
      ],
      "openSteps": [
        {
          "type": "tap",
          "point": {
            "x": 704,
            "y": 679
          },
          "label": "思案を開く",
          "area": {
            "x": 582,
            "y": 649,
            "width": 245,
            "height": 59
          }
        },
        {
          "type": "wait",
          "durationMs": 220,
          "label": "表示待ち"
        }
      ],
      "scanRegion": {
        "x": 90,
        "y": 84,
        "width": 1100,
        "height": 540
      },
      "scrollAxis": "vertical",
      "scrollDirection": "down",
      "scroll": {
        "start": {
          "x": 1080,
          "y": 610
        },
        "end": {
          "x": 1080,
          "y": 180
        },
        "durationMs": 450
      },
      "restoreSteps": [
        {
          "type": "back",
          "label": "元画面へ戻る"
        }
      ],
      "maxScrolls": 16,
      "endFingerprintStableCount": 2,
      "captureDelayMs": 160,
      "navigationNote": "思案表示をクリックして思案一覧を開く。構想の個数は思案の右に表示される。"
    },
    {
      "id": "is6CoinsFull",
      "label": "通宝フルスキャン",
      "triggerPath": "/trigger/scan/sui/coins",
      "campaignId": "is6_sui",
      "candidateKind": "coin",
      "baseResolution": {
        "width": 1280,
        "height": 720
      },
      "knownScreenIds": [
        "run-home",
        "sui-coin-list"
      ],
      "openSteps": [],
      "scanRegion": {
        "x": 120,
        "y": 96,
        "width": 1040,
        "height": 500
      },
      "scrollAxis": "horizontal",
      "scrollDirection": "right",
      "scroll": {
        "start": {
          "x": 1100,
          "y": 540
        },
        "end": {
          "x": 250,
          "y": 540
        },
        "durationMs": 450
      },
      "restoreSteps": [
        {
          "type": "back",
          "label": "元画面へ戻る"
        }
      ],
      "maxScrolls": 14,
      "endFingerprintStableCount": 2,
      "captureDelayMs": 160
    }
  ]
}
